treform/__init__.py
treform/version.py
treform/abbreviations/__init__.py
treform/abbreviations/candidate.py
treform/chunker/__init__.py
treform/collector/__init__.py
treform/collector/colAmericanNewsContent.py
treform/collector/colAmericanNewsURL.py
treform/collector/colBasic.py
treform/collector/colBigkinds.py
treform/collector/colChosun.py
treform/collector/colDonga.py
treform/collector/colJoongang.py
treform/collector/colNaverBlog.py
treform/collector/colNaverNews.py
treform/cooccurrence/__init__.py
treform/cooccurrence/cooccurrence.py
treform/counter/__init__.py
treform/document_classification/__init__.py
treform/document_classification/lasso_term_extraction.py
treform/document_classification/ml_textclassification.py
treform/document_clustering/__init__.py
treform/document_clustering/documentclustering.py
treform/graphml/__init__.py
treform/helper/__init__.py
treform/keyword/__init__.py
treform/keyword/ml_keyword_builder.py
treform/keyword/ml_keyword_extractor.py
treform/keyword/textrank.py
treform/lemmatizer/__init__.py
treform/ngram/__init__.py
treform/noun_extractor/__init__.py
treform/pmi/__init__.py
treform/segmentation/WordSemgmentationModelBuilder.py
treform/segmentation/__init__.py
treform/segmentation/wordSegmentationModelUtil.py
treform/sentiment/MLSentimentManager.py
treform/sentiment/__init__.py
treform/sentiment/englishDictionarySentimentAnalyzer.py
treform/sentiment/koreanDictionarySentimentAnalyzer.py
treform/sentiment/sentimentDataManager.py
treform/spelling/__init__.py
treform/spelling/config.py
treform/spelling/ngram_spelling_error_correction.py
treform/spelling/spelling_helper.py
treform/spelling/spelling_unicode.py
treform/spelling/symspell.py
treform/spelling/res/__init__.py
treform/splitter/__init__.py
treform/stemmer/__init__.py
treform/synonym/__init__.py
treform/synonym/generate_data.py
treform/synonym/train.py
treform/syntactic_parser/__init__.py
treform/tagger/__init__.py
treform/tokenizer/__init__.py
treform-1.1.18.dist-info/METADATA
treform-1.1.18.dist-info/WHEEL
treform-1.1.18.dist-info/top_level.txt
treform-1.1.18.dist-info/RECORD
