Metadata-Version: 2.1
Name: treform
Version: 1.1.18
Summary: A text mining tool for Korean and English
Home-page: https://github.com/MinSong2/treform
Author: Min Song
Author-email: min.song@yonsei.ac.kr
License: UNKNOWN
Platform: UNKNOWN
Classifier: Programming Language :: Python :: 3
Classifier: License :: OSI Approved :: MIT License
Classifier: Operating System :: OS Independent
Requires-Python: >=3.8
Requires-Dist: cython
Requires-Dist: seqeval
Requires-Dist: pytorch-crf
Requires-Dist: numpy
Requires-Dist: kiwipiepy
Requires-Dist: transformers
Requires-Dist: sklearn-crfsuite
Requires-Dist: gensim
Requires-Dist: konlpy
Requires-Dist: krwordrank
Requires-Dist: kss
Requires-Dist: lxml
Requires-Dist: matplotlib
Requires-Dist: networkx
Requires-Dist: node2vec
Requires-Dist: bs4
Requires-Dist: pycrfsuite-spacing
Requires-Dist: scikit-learn
Requires-Dist: scipy
Requires-Dist: seaborn
Requires-Dist: soynlp
Requires-Dist: torch
Requires-Dist: tomotopy
Requires-Dist: pyLDAvis
Requires-Dist: wordcloud
Requires-Dist: nltk
Requires-Dist: newspaper3k
Requires-Dist: selenium
Requires-Dist: soylemma
Requires-Dist: bokeh
Requires-Dist: beautifulsoup4
Requires-Dist: benepar (>=0.2.0)
Requires-Dist: symspellpy
